setup.py
src/wf_daobao/__init__.py
src/wf_daobao/gui.py
src/wf_daobao/json_peizhilei.py
src/wf_daobao/log_rizhi.py
src/wf_daobao/mk_dabao.py
src/wf_daobao/ui_treeview.py
src/wf_daobao.egg-info/PKG-INFO
src/wf_daobao.egg-info/SOURCES.txt
src/wf_daobao.egg-info/dependency_links.txt
src/wf_daobao.egg-info/requires.txt
src/wf_daobao.egg-info/top_level.txt