Metadata-Version: 2.1
Name: wf_daobao
Version: 20250816.4
Summary: pyinstaller_打包模块
Home-page: 
Author: xwf
Author-email: 453211170@qq.com
Classifier: Intended Audience :: Developers
Classifier: Operating System :: OS Independent
Classifier: Natural Language :: Chinese (Simplified)
Classifier: Programming Language :: Python :: 3
Classifier: Programming Language :: Python :: 3.2
Classifier: Programming Language :: Python :: 3.3
Classifier: Programming Language :: Python :: 3.4
Classifier: Programming Language :: Python :: 3.5
Classifier: Topic :: Utilities
Requires-Dist: pandas>=2.3.1
Requires-Dist: xlrd>=2.0.1
Requires-Dist: openpyxl>=3.1.2
Requires-Dist: pyperclip>=1.8.2
Requires-Dist: setuptools>=75.3.0
Requires-Dist: windnd>=1.0.7
Requires-Dist: loguru>=0.7.2
